src/__init__.py
src/ascii_file.py
asciiaks-0.0.1.dist-info/LICENCE.txt
asciiaks-0.0.1.dist-info/METADATA
asciiaks-0.0.1.dist-info/WHEEL
asciiaks-0.0.1.dist-info/top_level.txt
asciiaks-0.0.1.dist-info/RECORD
