Metadata-Version: 2.1
Name: asciiaks
Version: 0.0.1
Summary: Ascii Art
Home-page: UNKNOWN
Author: Akshay Kumar
Author-email: akshaykrsingh490@gmail.com
License: MIT
Keywords: art
Platform: UNKNOWN
Classifier: Development Status :: 5 - Production/Stable
Classifier: Intended Audience :: Education
Classifier: License :: OSI Approved :: MIT License
Classifier: Programming Language :: Python :: 3
Classifier: Programming Language :: Python :: 3.4
Classifier: Programming Language :: Python :: 3.5
Classifier: Programming Language :: Python :: 3.8
Classifier: Programming Language :: Python :: 3.9
Requires-Dist: Pillow
Requires-Dist: numpy
